bookmark_organizer/__init__.py
bookmark_organizer/cli.py
bookmark_organizer/core.py
bookmark_organizer/group_ideas.tsv
bookmark_organizer/report.py
bookmark_organizer-0.1.0.dist-info/METADATA
bookmark_organizer-0.1.0.dist-info/WHEEL
bookmark_organizer-0.1.0.dist-info/entry_points.txt
bookmark_organizer-0.1.0.dist-info/licenses/LICENSE
bookmark_organizer-0.1.0.dist-info/RECORD
