Metadata-Version: 2.4
Name: bookmark-organizer
Version: 0.1.0
Summary: A tool to organize and categorize bookmarks using AI
Project-URL: Homepage, https://github.com/neri/bookmark-organizer
Project-URL: Repository, https://github.com/neri/bookmark-organizer.git
Author-email: Uri Neri <uri.neri@gmail.com>
License-Expression: MIT
License-File: LICENSE
Classifier: Development Status :: 4 - Beta
Classifier: Intended Audience :: End Users/Desktop
Classifier: License :: OSI Approved :: MIT License
Classifier: Programming Language :: Python :: 3
Classifier: Programming Language :: Python :: 3.9
Classifier: Programming Language :: Python :: 3.10
Classifier: Programming Language :: Python :: 3.11
Requires-Python: >=3.9
Requires-Dist: beautifulsoup4>=4.13.3
Requires-Dist: openai>=1.72.0
Requires-Dist: python-dotenv>=1.1.0
Requires-Dist: tqdm>=4.67.1
